twat_search/__init__.py
twat_search/__main__.py
twat_search/__version__.py
twat_search/paths.py
twat_search/web/__init__.py
twat_search/web/api.py
twat_search/web/cli.py
twat_search/web/config.py
twat_search/web/engine_constants.py
twat_search/web/exceptions.py
twat_search/web/models.py
twat_search/web/utils.py
twat_search/web/engines/__init__.py
twat_search/web/engines/base.py
twat_search/web/engines/bing_scraper.py
twat_search/web/engines/brave.py
twat_search/web/engines/critique.py
twat_search/web/engines/duckduckgo.py
twat_search/web/engines/falla.py
twat_search/web/engines/google_scraper.py
twat_search/web/engines/hasdata.py
twat_search/web/engines/pplx.py
twat_search/web/engines/serpapi.py
twat_search/web/engines/tavily.py
twat_search/web/engines/you.py
twat_search/web/engines/lib_falla/__init__.py
twat_search/web/engines/lib_falla/main.py
twat_search/web/engines/lib_falla/requirements.txt
twat_search/web/engines/lib_falla/settings.py
twat_search/web/engines/lib_falla/utils.py
twat_search/web/engines/lib_falla/core/__init__.py
twat_search/web/engines/lib_falla/core/aol.py
twat_search/web/engines/lib_falla/core/ask.py
twat_search/web/engines/lib_falla/core/bing.py
twat_search/web/engines/lib_falla/core/dogpile.py
twat_search/web/engines/lib_falla/core/duckduckgo.py
twat_search/web/engines/lib_falla/core/falla.py
twat_search/web/engines/lib_falla/core/fetch_page.py
twat_search/web/engines/lib_falla/core/gibiru.py
twat_search/web/engines/lib_falla/core/google.py
twat_search/web/engines/lib_falla/core/mojeek.py
twat_search/web/engines/lib_falla/core/qwant.py
twat_search/web/engines/lib_falla/core/searchencrypt.py
twat_search/web/engines/lib_falla/core/startpage.py
twat_search/web/engines/lib_falla/core/yahoo.py
twat_search/web/engines/lib_falla/core/yandex.py
twat_search-2.7.0.dist-info/METADATA
twat_search-2.7.0.dist-info/WHEEL
twat_search-2.7.0.dist-info/entry_points.txt
twat_search-2.7.0.dist-info/licenses/LICENSE
twat_search-2.7.0.dist-info/RECORD
