Metadata-Version: 2.4
Name: twat-search
Version: 2.7.0
Summary: Web search plugin for twat
Project-URL: Documentation, https://github.com/twardoch/twat-search#readme
Project-URL: Issues, https://github.com/twardoch/twat-search/issues
Project-URL: Source, https://github.com/twardoch/twat-search
Author-email: Adam Twardoch <adam+github@twardoch.com>
License: MIT
License-File: LICENSE
Keywords: api,plugin,search,search-engine,twat,web,web-api,web-scraper,web-scraper-api,web-scraper-api-client,web-scraping,web-search
Classifier: Development Status :: 4 - Beta
Classifier: Intended Audience :: Developers
Classifier: License :: OSI Approved :: MIT License
Classifier: Operating System :: OS Independent
Classifier: Programming Language :: Python
Classifier: Programming Language :: Python :: 3.10
Classifier: Programming Language :: Python :: 3.11
Classifier: Programming Language :: Python :: 3.12
Classifier: Programming Language :: Python :: Implementation :: CPython
Classifier: Programming Language :: Python :: Implementation :: PyPy
Classifier: Topic :: Internet :: WWW/HTTP :: Indexing/Search
Requires-Python: >=3.10
Requires-Dist: beautifulsoup4>=4.13.0
Requires-Dist: fire>=0.7.0
Requires-Dist: httpx>=0.28.1
Requires-Dist: pydantic-settings>=2.8.1
Requires-Dist: pydantic>=2.10.6
Requires-Dist: python-dotenv>=1.0.1
Requires-Dist: requests>=2.32.3
Requires-Dist: rich>=13.9.4
Requires-Dist: twat-cache[all]>=2.6.7
Requires-Dist: twat>=2.7.0
Provides-Extra: all
Requires-Dist: duckduckgo-search>=7.5.0; extra == 'all'
Requires-Dist: googlesearch-python>=1.3.0; extra == 'all'
Requires-Dist: lxml>=5.3.1; extra == 'all'
Requires-Dist: playwright>=1.50.0; extra == 'all'
Requires-Dist: scrape-bing>=0.1.2.1; extra == 'all'
Requires-Dist: serpapi>=0.1.5; extra == 'all'
Requires-Dist: tavily-python>=0.5.1; extra == 'all'
Provides-Extra: bing-scraper
Requires-Dist: scrape-bing>=0.1.2.1; extra == 'bing-scraper'
Provides-Extra: brave
Provides-Extra: dev
Requires-Dist: absolufy-imports>=0.3.1; extra == 'dev'
Requires-Dist: isort>=6.0.1; extra == 'dev'
Requires-Dist: mypy>=1.15.0; extra == 'dev'
Requires-Dist: pre-commit>=4.1.0; extra == 'dev'
Requires-Dist: pyupgrade>=3.19.1; extra == 'dev'
Requires-Dist: ruff>=0.9.9; extra == 'dev'
Provides-Extra: docs
Requires-Dist: myst-parser>=4.0.1; extra == 'docs'
Requires-Dist: sphinx-autodoc-typehints>=3.1.0; extra == 'docs'
Requires-Dist: sphinx-rtd-theme>=3.0.2; extra == 'docs'
Requires-Dist: sphinx>=8.3.0; extra == 'docs'
Provides-Extra: duckduckgo
Requires-Dist: duckduckgo-search>=7.5.0; extra == 'duckduckgo'
Provides-Extra: falla
Requires-Dist: lxml>=5.3.1; extra == 'falla'
Requires-Dist: playwright>=1.50.0; extra == 'falla'
Provides-Extra: google-scraper
Requires-Dist: googlesearch-python>=1.3.0; extra == 'google-scraper'
Provides-Extra: hasdata
Provides-Extra: pplx
Provides-Extra: serpapi
Requires-Dist: serpapi>=0.1.5; extra == 'serpapi'
Provides-Extra: tavily
Requires-Dist: tavily-python>=0.5.1; extra == 'tavily'
Provides-Extra: test
Requires-Dist: coverage[toml]>=7.6.12; extra == 'test'
Requires-Dist: pytest-asyncio>=0.25.3; extra == 'test'
Requires-Dist: pytest-benchmark[histogram]>=5.1.0; extra == 'test'
Requires-Dist: pytest-cov>=6.0.0; extra == 'test'
Requires-Dist: pytest-xdist>=3.6.1; extra == 'test'
Requires-Dist: pytest>=8.3.5; extra == 'test'
